pyiceberg_hdfs_native.py
pyiceberg_hdfs_native-0.2.0.dist-info/licenses/LICENSE
pyiceberg_hdfs_native-0.2.0.dist-info/METADATA
pyiceberg_hdfs_native-0.2.0.dist-info/WHEEL
pyiceberg_hdfs_native-0.2.0.dist-info/top_level.txt
pyiceberg_hdfs_native-0.2.0.dist-info/RECORD
