Metadata-Version: 2.4
Name: pyiceberg-hdfs-native
Version: 0.2.0
Summary: Provides a pyiceberg.io.FileIO implementation for hdfs-native client
Requires-Python: >=3.9
License-File: LICENSE
Requires-Dist: hdfs-native>=0.12
Requires-Dist: pyiceberg>=0.9
Dynamic: license-file
